jrt/__init__.py
jrt/builder.py
jrt/cli.py
jrt/constants.py
jrt/ontology.py
jrt-0.3.2.dist-info/LICENSE
jrt-0.3.2.dist-info/METADATA
jrt-0.3.2.dist-info/WHEEL
jrt-0.3.2.dist-info/entry_points.txt
jrt-0.3.2.dist-info/RECORD
