Metadata-Version: 2.3
Name: jrt
Version: 0.3.2
Summary: A JSON to RDF transformer library that maps arbitrary JSON to RDF using heuristics and ontologies.
License: MIT
Keywords: json,rdf,cli,ontology,semantic web,linked data
Author: Mathieu 'Bloodbee' Dufour
Author-email: mathieu@bloodbee.space
Requires-Python: >=3.10,<4.0
Classifier: License :: OSI Approved :: MIT License
Classifier: Programming Language :: Python :: 3
Classifier: Programming Language :: Python :: 3.10
Classifier: Programming Language :: Python :: 3.11
Classifier: Programming Language :: Python :: 3.12
Classifier: Programming Language :: Python :: 3.13
Requires-Dist: jsonpath-ng (>=1.6.0,<2.0.0)
Requires-Dist: rdflib (>=7.0.0,<8.0.0)
Requires-Dist: typer
Project-URL: Homepage, https://github.com/bloodbee/jrt
Project-URL: Repository, https://github.com/bloodbee/jrt
